simaple/__init__.py
simaple/app/__init__.py
simaple/app/application/__init__.py
simaple/app/application/command/__init__.py
simaple/app/application/command/simulator.py
simaple/app/application/command/snapshot.py
simaple/app/application/exception.py
simaple/app/application/query/__init__.py
simaple/app/application/query/component_spec.py
simaple/app/application/query/skill.py
simaple/app/application/query/snapshot.py
simaple/app/domain/__init__.py
simaple/app/domain/component_schema.py
simaple/app/domain/services/__init__.py
simaple/app/domain/services/plan.py
simaple/app/domain/services/statistics.py
simaple/app/domain/simulator.py
simaple/app/domain/snapshot.py
simaple/app/domain/uow.py
simaple/app/infrastructure/__init__.py
simaple/app/infrastructure/component_schema_repository.py
simaple/app/infrastructure/configuration_mapper.py
simaple/app/infrastructure/inmemory.py
simaple/app/infrastructure/orm.py
simaple/app/infrastructure/repository.py
simaple/app/infrastructure/snapshot_repository.py
simaple/app/infrastructure/uow.py
simaple/app/interface/__init__.py
simaple/app/interface/container.py
simaple/app/interface/handler.py
simaple/app/interface/routers/__init__.py
simaple/app/interface/routers/base.py
simaple/app/interface/routers/component_spec.py
simaple/app/interface/routers/skill.py
simaple/app/interface/routers/snapshot.py
simaple/app/interface/routers/statistics.py
simaple/app/interface/routers/workspace.py
simaple/app/interface/static/assets/index-34865b96.js
simaple/app/interface/static/index.html
simaple/app/interface/static/vite.svg
simaple/app/interface/web.py
simaple/app/wasm/__init__.py
simaple/app/wasm/base.py
simaple/app/wasm/skill.py
simaple/app/wasm/workspace.py
simaple/character/__init__.py
simaple/character/character.py
simaple/character/readme.md
simaple/container/__init__.py
simaple/container/simulation.py
simaple/core/__init__.py
simaple/core/base.py
simaple/core/damage.py
simaple/core/job_category.py
simaple/core/jobtype.py
simaple-0.4.2.dist-info/LICENSE
simaple-0.4.2.dist-info/METADATA
simaple-0.4.2.dist-info/WHEEL
simaple-0.4.2.dist-info/RECORD
