Metadata-Version: 2.1
Name: simaple
Version: 0.4.2
Summary: Maplestory calculation / Simulation library
Home-page: https://github.com/simaple-team/simaple
License: MIT
Author: meson324
Author-email: meson324@gmail.com
Requires-Python: >=3.10,<3.13
Classifier: License :: OSI Approved :: MIT License
Classifier: Programming Language :: Python :: 3
Classifier: Programming Language :: Python :: 3.10
Classifier: Programming Language :: Python :: 3.11
Classifier: Programming Language :: Python :: 3.12
Requires-Dist: PyYAML (>=6.0,<7.0)
Requires-Dist: SQLAlchemy (>=1.4.45,<2.0.0)
Requires-Dist: aiohttp (>=3.10.1,<4.0.0)
Requires-Dist: dependency-injector (>=4.40.0,<5.0.0)
Requires-Dist: fastapi (>=0.110.1,<0.111.0)
Requires-Dist: fire (>=0.4.0,<0.5.0)
Requires-Dist: lark (>=1.1.7,<2.0.0)
Requires-Dist: loguru (>=0.5.3,<0.6.0)
Requires-Dist: numpy (>=1.22.3,<2.0.0)
Requires-Dist: pydantic (>=2.4.2,<3.0.0)
Requires-Dist: pydantic-settings (>=2.0.3,<3.0.0)
Requires-Dist: pyfunctional (>=1.5.0,<2.0.0)
Requires-Dist: requests (>=2.26.0,<3.0.0)
Requires-Dist: scikit-learn (>=1.0.2,<2.0.0)
Requires-Dist: scipy (>=1.11.2,<2.0.0)
Requires-Dist: uvicorn (>=0.20.0,<0.21.0)
Project-URL: Repository, https://github.com/simaple-team/simaple
